{
  "backgrounds": [
    {
      "url": "/theme-img/background1.jpg",
      "name": "无昼之海"
    },
    {
      "url": "/theme-img/background2.jpg",
      "name": "沙石镇时光"
    },
    {
      "url": "/theme-img/background3.jpg",
      "name": "龙石战争"
    },
    {
      "url": "/theme-img/background4.jpg",
      "name": "塔瑞斯世界"
    },
    {
      "url": "/theme-img/background5.jpg",
      "name": "湮灭之潮"
    },
    {
      "url": "/theme-img/background6.png",
      "name": "Arc Raiders"
    }
  ],
  "interval": 5000,
  "transition": 1000
}
